pyrf96.libs/libgfortran-040039e1.so.5.0.0
pyrf96.libs/libquadmath-96973f99.so.0.0.0
pyrf96-0.1.0.dist-info/RECORD
pyrf96-0.1.0.dist-info/METADATA
pyrf96-0.1.0.dist-info/WHEEL
pyrf96-0.1.0.dist-info/licenses/LICENSE
pyrf96/rf96.cpython-312-x86_64-linux-gnu.so
pyrf96/__init__.py
pyrf96/_pyrf96.py
