Metadata-Version: 2.1
Name: pyrf96
Version: 0.1.0
Requires-Python: >=3.9
Requires-Dist: numpy
Requires-Dist: matplotlib
